{
  "replace": false,
  "values": [
    {
      "id": "immersiveengineering:seed",
      "required": false
    },
    {
      "id": "thermal:barley",
      "required": false
    },
    {
      "id": "thermal:corn",
      "required": false
    },
    {
      "id": "thermal:onion",
      "required": false
    },
    {
      "id": "thermal:bell_pepper",
      "required": false
    },
    {
      "id": "thermal:eggplant",
      "required": false
    },
    {
      "id": "thermal:green_bean",
      "required": false
    },
    {
      "id": "thermal:strawberry",
      "required": false
    },
    {
      "id": "thermal:tomato",
      "required": false
    },
    {
      "id": "thermal:tea",
      "required": false
    }
  ]
}